odoo/addons/tanit_services_inventory/.gitignore
odoo/addons/tanit_services_inventory/__init__.py
odoo/addons/tanit_services_inventory/__manifest__.py
odoo/addons/tanit_services_inventory/demo/demo.xml
odoo/addons/tanit_services_inventory/models/__init__.py
odoo/addons/tanit_services_inventory/models/service.py
odoo/addons/tanit_services_inventory/models/service_feature.py
odoo/addons/tanit_services_inventory/models/service_feature_type.py
odoo/addons/tanit_services_inventory/models/service_type.py
odoo/addons/tanit_services_inventory/security/ir.model.access.csv
odoo/addons/tanit_services_inventory/static/description/icon.png
odoo/addons/tanit_services_inventory/static/src/img/icon.png
odoo/addons/tanit_services_inventory/views/dashboard.xml
odoo/addons/tanit_services_inventory/views/service.xml
odoo/addons/tanit_services_inventory/views/service_feature.xml
odoo/addons/tanit_services_inventory/views/service_feature_type.xml
odoo/addons/tanit_services_inventory/views/service_type.xml
odoo14_addon_tanit_services_inventory-14.0.0.0.6.dist-info/METADATA
odoo14_addon_tanit_services_inventory-14.0.0.0.6.dist-info/WHEEL
odoo14_addon_tanit_services_inventory-14.0.0.0.6.dist-info/top_level.txt
odoo14_addon_tanit_services_inventory-14.0.0.0.6.dist-info/RECORD
